xbeastx/__init__.py
xbeastx-0.1.dist-info/METADATA
xbeastx-0.1.dist-info/WHEEL
xbeastx-0.1.dist-info/top_level.txt
xbeastx-0.1.dist-info/RECORD
