Metadata-Version: 2.2
Name: xbeastx
Version: 0.1
Summary: A package that imports all required dependencies.
Home-page: https://github.com/msy1717/xbeastx
Author: Your Name
Author-email: atronpay7@gmail.com
Classifier: Programming Language :: Python :: 3
Classifier: License :: OSI Approved :: MIT License
Classifier: Operating System :: OS Independent
Requires-Python: >=3.6
Requires-Dist: Flask
Requires-Dist: Telethon
Requires-Dist: APScheduler
Requires-Dist: requests
Requires-Dist: pytz
Requires-Dist: pyrogram
Requires-Dist: pymongo
Requires-Dist: colorama
Requires-Dist: localdb.json
Requires-Dist: lolpy
Dynamic: author
Dynamic: author-email
Dynamic: classifier
Dynamic: home-page
Dynamic: requires-dist
Dynamic: requires-python
Dynamic: summary
